src/1_cycle_part/secded_decoder.sv
module secded_decoder (
  input  logic        CLK,
  input  logic [71:0] E_DATA,
  output logic [71:0] D_DATA,
  output logic        ERR,
  output logic        D_ERR,
  output logic        S_ERR
);

  logic [7:0]  SYNDROME;
  logic [71:0] MASK;
  logic        OR_SYND;
  logic        XOR_SYND;

  assign OR_SYND  = |SYNDROME;
  assign XOR_SYND = ^SYNDROME;

    // S1
    assign SYNDROME[0] = E_DATA[0] ^ E_DATA[1] ^ E_DATA[2] ^ E_DATA[3] ^ E_DATA[4] ^ E_DATA[5] ^ E_DATA[6] ^
	    E_DATA[7] ^ E_DATA[10] ^ E_DATA[13] ^ E_DATA[14] ^ E_DATA[17] ^ E_DATA[20] ^ E_DATA[23] ^
		  E_DATA[24] ^ E_DATA[27] ^ E_DATA[35] ^ E_DATA[43] ^ E_DATA[46] ^ E_DATA[47] ^ E_DATA[51] ^
		  E_DATA[52] ^ E_DATA[53] ^ E_DATA[56] ^ E_DATA[57] ^ E_DATA[58] ^ E_DATA[64];
    
    // S2
    assign SYNDROME[1] = E_DATA[0] ^ E_DATA[1] ^ E_DATA[2] ^ E_DATA[8] ^ E_DATA[9] ^ E_DATA[10] ^ E_DATA[11] ^
	    E_DATA[12] ^ E_DATA[13] ^ E_DATA[14] ^ E_DATA[15] ^ E_DATA[18] ^ E_DATA[21] ^ E_DATA[22] ^
		  E_DATA[25] ^ E_DATA[28] ^ E_DATA[31] ^ E_DATA[32] ^ E_DATA[35] ^ E_DATA[43] ^ E_DATA[51] ^
		  E_DATA[54] ^ E_DATA[55] ^ E_DATA[59] ^ E_DATA[60] ^ E_DATA[61] ^ E_DATA[65];

    // S3
    assign SYNDROME[2] = E_DATA[3] ^ E_DATA[4] ^ E_DATA[5] ^ E_DATA[8] ^ E_DATA[9] ^ E_DATA[10] ^ E_DATA[16] ^
	    E_DATA[17] ^ E_DATA[18] ^ E_DATA[19] ^ E_DATA[20] ^ E_DATA[21] ^ E_DATA[22] ^ E_DATA[23] ^
		  E_DATA[26] ^ E_DATA[29] ^ E_DATA[30] ^ E_DATA[33] ^ E_DATA[36] ^ E_DATA[39] ^ E_DATA[40] ^
		  E_DATA[43] ^ E_DATA[51] ^ E_DATA[59] ^ E_DATA[62] ^ E_DATA[63] ^ E_DATA[66];

    // S4
    assign SYNDROME[3] = E_DATA[3] ^ E_DATA[6] ^ E_DATA[7] ^ E_DATA[11] ^ E_DATA[12] ^ E_DATA[13] ^ E_DATA[16] ^ 
		  E_DATA[17] ^ E_DATA[18] ^ E_DATA[24] ^ E_DATA[25] ^ E_DATA[26] ^ E_DATA[27] ^ E_DATA[28] ^ 
		  E_DATA[29] ^ E_DATA[30] ^ E_DATA[31] ^ E_DATA[34] ^ E_DATA[37] ^ E_DATA[38] ^ E_DATA[41] ^ 
		  E_DATA[44] ^ E_DATA[47] ^ E_DATA[48] ^ E_DATA[51] ^ E_DATA[59] ^ E_DATA[67];

    // S5
    assign SYNDROME[4] = E_DATA[3] ^ E_DATA[11] ^ E_DATA[14] ^ E_DATA[15] ^ E_DATA[19] ^ E_DATA[20] ^ E_DATA[21] ^
	    E_DATA[24] ^ E_DATA[25] ^ E_DATA[26] ^ E_DATA[32] ^ E_DATA[33] ^ E_DATA[34] ^ E_DATA[35] ^
		  E_DATA[36] ^ E_DATA[37] ^ E_DATA[38] ^ E_DATA[39] ^ E_DATA[42] ^ E_DATA[45] ^ E_DATA[46] ^
		  E_DATA[49] ^ E_DATA[52] ^ E_DATA[55] ^ E_DATA[56] ^ E_DATA[59] ^ E_DATA[68];

    // S6
    assign SYNDROME[5] = E_DATA[0] ^ E_DATA[3] ^ E_DATA[11] ^ E_DATA[19] ^ E_DATA[22] ^ E_DATA[23] ^ E_DATA[27] ^
	    E_DATA[28] ^ E_DATA[29] ^ E_DATA[32] ^ E_DATA[33] ^ E_DATA[34] ^ E_DATA[40] ^ E_DATA[41] ^
		  E_DATA[42] ^ E_DATA[43] ^ E_DATA[44] ^ E_DATA[45] ^ E_DATA[46] ^ E_DATA[47] ^ E_DATA[50] ^
		  E_DATA[53] ^ E_DATA[54] ^ E_DATA[57] ^ E_DATA[60] ^ E_DATA[63] ^ E_DATA[69];

    // S7
    assign SYNDROME[6] = E_DATA[1] ^ E_DATA[4] ^ E_DATA[7] ^ E_DATA[8] ^ E_DATA[11] ^ E_DATA[19] ^ E_DATA[27] ^
	    E_DATA[30] ^ E_DATA[31] ^ E_DATA[35] ^ E_DATA[36] ^ E_DATA[37] ^ E_DATA[40] ^ E_DATA[41] ^
		  E_DATA[42] ^ E_DATA[48] ^ E_DATA[49] ^ E_DATA[50] ^ E_DATA[51] ^ E_DATA[52] ^ E_DATA[53] ^
		  E_DATA[54] ^ E_DATA[55] ^ E_DATA[58] ^ E_DATA[61] ^ E_DATA[62] ^ E_DATA[70];

    // S8
    assign SYNDROME[7] = E_DATA[2] ^ E_DATA[5] ^ E_DATA[6] ^ E_DATA[9] ^ E_DATA[12] ^ E_DATA[15] ^ E_DATA[16] ^
	    E_DATA[19] ^ E_DATA[27] ^ E_DATA[35] ^ E_DATA[38] ^ E_DATA[39] ^ E_DATA[43] ^ E_DATA[44] ^
		  E_DATA[45] ^ E_DATA[48] ^ E_DATA[49] ^ E_DATA[50] ^ E_DATA[56] ^ E_DATA[57] ^ E_DATA[58] ^
		  E_DATA[59] ^ E_DATA[60] ^ E_DATA[61] ^ E_DATA[62] ^ E_DATA[63] ^ E_DATA[71];

  always @(posedge CLK) begin
    ERR      <= OR_SYND;
    D_ERR    <= OR_SYND & !XOR_SYND;
    S_ERR    <= OR_SYND & XOR_SYND;
    D_DATA   <= MASK ^ E_DATA;
    
  end

  always @(*) begin
    case (SYNDROME) 
      8'b00100011: MASK = 72'h00_0000_0000_0000_0001; // E_DATA[0]
      8'b01000011: MASK = 72'h00_0000_0000_0000_0002; // E_DATA[1]
      8'b10000011: MASK = 72'h00_0000_0000_0000_0004; // E_DATA[2]
      8'b00111101: MASK = 72'h00_0000_0000_0000_0008; // E_DATA[3]
      8'b01000101: MASK = 72'h00_0000_0000_0000_0010; // E_DATA[4]
      8'b10000101: MASK = 72'h00_0000_0000_0000_0020; // E_DATA[5]
      8'b10001001: MASK = 72'h00_0000_0000_0000_0040; // E_DATA[6]
      8'b01001001: MASK = 72'h00_0000_0000_0000_0080; // E_DATA[7]
      8'b01000110: MASK = 72'h00_0000_0000_0000_0100; // E_DATA[8]
      8'b10000110: MASK = 72'h00_0000_0000_0000_0200; // E_DATA[9]
      8'b00000111: MASK = 72'h00_0000_0000_0000_0400; // E_DATA[10]
      8'b01111010: MASK = 72'h00_0000_0000_0000_0800; // E_DATA[11]
      8'b10001010: MASK = 72'h00_0000_0000_0000_1000; // E_DATA[12]
      8'b00001011: MASK = 72'h00_0000_0000_0000_2000; // E_DATA[13]
      8'b00010011: MASK = 72'h00_0000_0000_0000_4000; // E_DATA[14]
      8'b10010010: MASK = 72'h00_0000_0000_0000_8000; // E_DATA[15]
      8'b10001100: MASK = 72'h00_0000_0000_0001_0000; // E_DATA[16]
      8'b00001101: MASK = 72'h00_0000_0000_0002_0000; // E_DATA[17]
      8'b00001110: MASK = 72'h00_0000_0000_0004_0000; // E_DATA[18]
      8'b11110100: MASK = 72'h00_0000_0000_0008_0000; // E_DATA[19]
      8'b00010101: MASK = 72'h00_0000_0000_0010_0000; // E_DATA[20]
      8'b00010110: MASK = 72'h00_0000_0000_0020_0000; // E_DATA[21]
      8'b00100110: MASK = 72'h00_0000_0000_0040_0000; // E_DATA[22]
      8'b00100101: MASK = 72'h00_0000_0000_0080_0000; // E_DATA[23]
      8'b00011001: MASK = 72'h00_0000_0000_0100_0000; // E_DATA[24]
      8'b00011010: MASK = 72'h00_0000_0000_0200_0000; // E_DATA[25]
      8'b00011100: MASK = 72'h00_0000_0000_0400_0000; // E_DATA[26]
      8'b11101001: MASK = 72'h00_0000_0000_0800_0000; // E_DATA[27]
      8'b00101010: MASK = 72'h00_0000_0000_1000_0000; // E_DATA[28]
      8'b00101100: MASK = 72'h00_0000_0000_2000_0000; // E_DATA[29]
      8'b01001100: MASK = 72'h00_0000_0000_4000_0000; // E_DATA[30]
      8'b01001010: MASK = 72'h00_0000_0000_8000_0000; // E_DATA[31]
      8'b00110010: MASK = 72'h00_0000_0001_0000_0000; // E_DATA[32]
      8'b00110100: MASK = 72'h00_0000_0002_0000_0000; // E_DATA[33]
      8'b00111000: MASK = 72'h00_0000_0004_0000_0000; // E_DATA[34]
      8'b11010011: MASK = 72'h00_0000_0008_0000_0000; // E_DATA[35]
      8'b01010100: MASK = 72'h00_0000_0010_0000_0000; // E_DATA[36]
      8'b01011000: MASK = 72'h00_0000_0020_0000_0000; // E_DATA[37]
      8'b10011000: MASK = 72'h00_0000_0040_0000_0000; // E_DATA[38]
      8'b10010100: MASK = 72'h00_0000_0080_0000_0000; // E_DATA[39]
      8'b01100100: MASK = 72'h00_0000_0100_0000_0000; // E_DATA[40]
      8'b01101000: MASK = 72'h00_0000_0200_0000_0000; // E_DATA[41]
      8'b01110000: MASK = 72'h00_0000_0400_0000_0000; // E_DATA[42]
      8'b10100111: MASK = 72'h00_0000_0800_0000_0000; // E_DATA[43]
      8'b10101000: MASK = 72'h00_0000_1000_0000_0000; // E_DATA[44]
      8'b10110000: MASK = 72'h00_0000_2000_0000_0000; // E_DATA[45]
      8'b00110001: MASK = 72'h00_0000_4000_0000_0000; // E_DATA[46]
      8'b00101001: MASK = 72'h00_0000_8000_0000_0000; // E_DATA[47]
      8'b11001000: MASK = 72'h00_0001_0000_0000_0000; // E_DATA[48]
      8'b11010000: MASK = 72'h00_0002_0000_0000_0000; // E_DATA[49]
      8'b11100000: MASK = 72'h00_0004_0000_0000_0000; // E_DATA[50]
      8'b01001111: MASK = 72'h00_0008_0000_0000_0000; // E_DATA[51]
      8'b01010001: MASK = 72'h00_0010_0000_0000_0000; // E_DATA[52]
      8'b01100001: MASK = 72'h00_0020_0000_0000_0000; // E_DATA[53]
      8'b01100010: MASK = 72'h00_0040_0000_0000_0000; // E_DATA[54]
      8'b01010010: MASK = 72'h00_0080_0000_0000_0000; // E_DATA[55]
      8'b10010001: MASK = 72'h00_0100_0000_0000_0000; // E_DATA[56]
      8'b10100001: MASK = 72'h00_0200_0000_0000_0000; // E_DATA[57]
      8'b11000001: MASK = 72'h00_0400_0000_0000_0000; // E_DATA[58]
      8'b10011110: MASK = 72'h00_0800_0000_0000_0000; // E_DATA[59]
      8'b10100010: MASK = 72'h00_1000_0000_0000_0000; // E_DATA[60]
      8'b11000010: MASK = 72'h00_2000_0000_0000_0000; // E_DATA[61]
      8'b11000100: MASK = 72'h00_4000_0000_0000_0000; // E_DATA[62]
      8'b10100100: MASK = 72'h00_8000_0000_0000_0000; // E_DATA[63]
      8'b00000001: MASK = 72'h01_0000_0000_0000_0000; // E_DATA[64]
      8'b00000010: MASK = 72'h02_0000_0000_0000_0000; // E_DATA[65]
      8'b00000100: MASK = 72'h04_0000_0000_0000_0000; // E_DATA[66]
      8'b00001000: MASK = 72'h08_0000_0000_0000_0000; // E_DATA[67]
      8'b00010000: MASK = 72'h10_0000_0000_0000_0000; // E_DATA[68]
      8'b00100000: MASK = 72'h20_0000_0000_0000_0000; // E_DATA[69]
      8'b01000000: MASK = 72'h40_0000_0000_0000_0000; // E_DATA[70]
      8'b10000000: MASK = 72'h80_0000_0000_0000_0000; // E_DATA[71]
      default:     MASK = 72'h00_0000_0000_0000_0000; // no error
    endcase
   end
endmodule

src/1_cycle_tot/secded_encoder.sv
module secded_encoder (
  input  logic        CLK,
  input  logic [63:0] R_DATA,
  output logic [71:0] E_DATA
);

  logic [71:0] BUFFER;

  assign E_DATA = BUFFER;

  always @(posedge CLK) begin
    BUFFER [63:0] <= R_DATA;
  
    // C1
    BUFFER[64] <= R_DATA[0] ^ R_DATA[1] ^ R_DATA[2] ^ R_DATA[3] ^ R_DATA[4] ^ R_DATA[5] ^ R_DATA[6] ^
      R_DATA[7] ^ R_DATA[10] ^ R_DATA[13] ^ R_DATA[14] ^ R_DATA[17] ^ R_DATA[20] ^ R_DATA[23] ^
		  R_DATA[24] ^ R_DATA[27] ^ R_DATA[35] ^ R_DATA[43] ^ R_DATA[46] ^ R_DATA[47] ^ R_DATA[51] ^
		  R_DATA[52] ^ R_DATA[53] ^ R_DATA[56] ^ R_DATA[57] ^ R_DATA[58];
    // C2
    BUFFER[65] <= R_DATA[0] ^ R_DATA[1] ^ R_DATA[2] ^ R_DATA[8] ^ R_DATA[9] ^ R_DATA[10] ^ R_DATA[11] ^
  	  R_DATA[12] ^ R_DATA[13] ^ R_DATA[14] ^ R_DATA[15] ^ R_DATA[18] ^ R_DATA[21] ^ R_DATA[22] ^
  		R_DATA[25] ^ R_DATA[28] ^ R_DATA[31] ^ R_DATA[32] ^ R_DATA[35] ^ R_DATA[43] ^ R_DATA[51] ^
  	  R_DATA[54] ^ R_DATA[55] ^ R_DATA[59] ^ R_DATA[60] ^ R_DATA[61];
  
    // C3
    BUFFER[66] <= R_DATA[3] ^ R_DATA[4] ^ R_DATA[5] ^ R_DATA[8] ^ R_DATA[9] ^ R_DATA[10] ^ R_DATA[16] ^
  	  R_DATA[17] ^ R_DATA[18] ^ R_DATA[19] ^ R_DATA[20] ^ R_DATA[21] ^ R_DATA[22] ^ R_DATA[23] ^
  		R_DATA[26] ^ R_DATA[29] ^ R_DATA[30] ^ R_DATA[33] ^ R_DATA[36] ^ R_DATA[39] ^ R_DATA[40] ^
  	  R_DATA[43] ^ R_DATA[51] ^ R_DATA[59] ^ R_DATA[62] ^ R_DATA[63];
  
    // C4
    BUFFER[67] <= R_DATA[3] ^ R_DATA[6] ^ R_DATA[7] ^ R_DATA[11] ^ R_DATA[12] ^ R_DATA[13] ^ R_DATA[16] ^ 
  		R_DATA[17] ^ R_DATA[18] ^ R_DATA[24] ^ R_DATA[25] ^ R_DATA[26] ^ R_DATA[27] ^ R_DATA[28] ^ 
  	  R_DATA[29] ^ R_DATA[30] ^ R_DATA[31] ^ R_DATA[34] ^ R_DATA[37] ^ R_DATA[38] ^ R_DATA[41] ^ 
  	  R_DATA[44] ^ R_DATA[47] ^ R_DATA[48] ^ R_DATA[51] ^ R_DATA[59];
  
    // C5
    BUFFER[68] <= R_DATA[3] ^ R_DATA[11] ^ R_DATA[14] ^ R_DATA[15] ^ R_DATA[19] ^ R_DATA[20] ^ R_DATA[21] ^
  	  R_DATA[24] ^ R_DATA[25] ^ R_DATA[26] ^ R_DATA[32] ^ R_DATA[33] ^ R_DATA[34] ^ R_DATA[35] ^
  		R_DATA[36] ^ R_DATA[37] ^ R_DATA[38] ^ R_DATA[39] ^ R_DATA[42] ^ R_DATA[45] ^ R_DATA[46] ^
  	  R_DATA[49] ^ R_DATA[52] ^ R_DATA[55] ^ R_DATA[56] ^ R_DATA[59];
  
    // C6
    BUFFER[69] <= R_DATA[0] ^ R_DATA[3] ^ R_DATA[11] ^ R_DATA[19] ^ R_DATA[22] ^ R_DATA[23] ^ R_DATA[27] ^
  	  R_DATA[28] ^ R_DATA[29] ^ R_DATA[32] ^ R_DATA[33] ^ R_DATA[34] ^ R_DATA[40] ^ R_DATA[41] ^
  		R_DATA[42] ^ R_DATA[43] ^ R_DATA[44] ^ R_DATA[45] ^ R_DATA[46] ^ R_DATA[47] ^ R_DATA[50] ^
  		R_DATA[53] ^ R_DATA[54] ^ R_DATA[57] ^ R_DATA[60] ^ R_DATA[63];

    // C7
    BUFFER[70] <= R_DATA[1] ^ R_DATA[4] ^ R_DATA[7] ^ R_DATA[8] ^ R_DATA[11] ^ R_DATA[19] ^ R_DATA[27] ^
      R_DATA[30] ^ R_DATA[31] ^ R_DATA[35] ^ R_DATA[36] ^ R_DATA[37] ^ R_DATA[40] ^ R_DATA[41] ^
      R_DATA[42] ^ R_DATA[48] ^ R_DATA[49] ^ R_DATA[50] ^ R_DATA[51] ^ R_DATA[52] ^ R_DATA[53] ^
      R_DATA[54] ^ R_DATA[55] ^ R_DATA[58] ^ R_DATA[61] ^ R_DATA[62];

    // C8
    BUFFER[71] <= R_DATA[2] ^ R_DATA[5] ^ R_DATA[6] ^ R_DATA[9] ^ R_DATA[12] ^ R_DATA[15] ^ R_DATA[16] ^
      R_DATA[19] ^ R_DATA[27] ^ R_DATA[35] ^ R_DATA[38] ^ R_DATA[39] ^ R_DATA[43] ^ R_DATA[44] ^
     	R_DATA[45] ^ R_DATA[48] ^ R_DATA[49] ^ R_DATA[50] ^ R_DATA[56] ^ R_DATA[57] ^ R_DATA[58] ^
      R_DATA[59] ^ R_DATA[60] ^ R_DATA[61] ^ R_DATA[62] ^ R_DATA[63];
  end 
endmodule

src/1_cycle_tot/testbench.sv
module testbench;
  logic CLK;
  logic [63:0] R_DATA;
  logic [71:0] E_DATA;
  logic [71:0] D_DATA;
  logic        ERR;
  logic        D_ERR;
  logic        S_ERR;
  logic [71:0] N_DATA;
  logic [71:0] NOISE;

  string dumpfile_name;

  secded_encoder dut_encoder (
    .CLK (CLK),
    .R_DATA (R_DATA),
    .E_DATA (E_DATA)
  );

  secded_decoder dut_decoder (
    .CLK (CLK),
    .E_DATA (N_DATA),
    .D_DATA (D_DATA),
    .ERR (ERR),
    .D_ERR (D_ERR),
    .S_ERR (S_ERR)
  );

  initial begin
    CLK = 1'b0;
    forever #5 CLK = ~CLK;
  end

  initial begin
    $monitor("time=%3d, data=%h, encoded=%h, decoded=%h, error_detected=%b, double_error=%b, single_error=%b", $time, R_DATA, E_DATA, D_DATA, ERR, D_ERR, S_ERR);
    #2
    R_DATA = 64'hDEAD_BEEF_CAFE_CAFE;
    #10
    R_DATA = 64'hCAFE_CAFE_DEAD_BEEF;
    #10
    R_DATA = 64'h1212_3434_5656_7878;
    #10
    R_DATA = 64'hDEAD_BEEF_CAFE_CAFE;
    #10
    R_DATA = 64'hCAFE_CAFE_DEAD_BEEF;
    #10
    R_DATA = 64'h1212_3434_5656_7878;
    #10
    R_DATA = 64'hDEAD_BEEF_CAFE_CAFE;
    #10
    R_DATA = 64'hCAFE_CAFE_DEAD_BEEF;
    #10
    R_DATA = 64'h1212_3434_5656_7878;
    #50
    $finish;
  end

  initial begin
    NOISE = 72'h00_0000_0000_0000_0000; // NO ERR
    #37
    NOISE = 72'h00_0000_0000_0010_0000; // SEC
    #30
    NOISE = 72'h00_0110_0000_0000_0000; // DED
  end

  assign N_DATA = E_DATA ^ NOISE;

  initial begin
    if ($value$plusargs("dumpfile=%s", dumpfile_name))
      $dumpfile(dumpfile_name);
    else
      $dumpfile("generic_waveform.vcd");
    $dumpvars(0, testbench);
  end
endmodule

build/1_cycle_part/waveform.vcd
$version Generated by VerilatedVcd $end
$timescale 1ps $end
 $scope module TOP $end
  $scope module testbench $end
   $var wire 1 8 CLK $end
   $var wire 64 9 R_DATA [63:0] $end
   $var wire 72 , E_DATA [71:0] $end
   $var wire 72 / D_DATA [71:0] $end
   $var wire 1 2 ERR $end
   $var wire 1 3 D_ERR $end
   $var wire 1 4 S_ERR $end
   $var wire 72 # N_DATA [71:0] $end
   $var wire 72 ; NOISE [71:0] $end
   $scope module dut_decoder $end
    $var wire 1 8 CLK $end
    $var wire 72 # E_DATA [71:0] $end
    $var wire 72 / D_DATA [71:0] $end
    $var wire 1 2 ERR $end
    $var wire 1 3 D_ERR $end
    $var wire 1 4 S_ERR $end
    $var wire 8 & SYNDROME [7:0] $end
    $var wire 72 ' MASK [71:0] $end
    $var wire 1 * OR_SYND $end
    $var wire 1 + XOR_SYND $end
   $upscope $end
   $scope module dut_encoder $end
    $var wire 1 8 CLK $end
    $var wire 64 9 R_DATA [63:0] $end
    $var wire 72 , E_DATA [71:0] $end
    $var wire 72 5 BUFFER [71:0] $end
   $upscope $end
  $upscope $end
 $upscope $end
$enddefinitions $end


#0
b000000000000000000000000000000000000000000000000000000000000000000000000 #
b00000000 &
b000000000000000000000000000000000000000000000000000000000000000000000000 '
0*
0+
b000000000000000000000000000000000000000000000000000000000000000000000000 ,
b000000000000000000000000000000000000000000000000000000000000000000000000 /
02
03
04
b000000000000000000000000000000000000000000000000000000000000000000000000 5
08
b0000000000000000000000000000000000000000000000000000000000000000 9
b000000000000000000000000000000000000000000000000000000000000000000000000 ;
#2
b1101111010101101101111101110111111001010111111101100101011111110 9
#5
b110111011101111010101101101111101110111111001010111111101100101011111110 5
18
#10
08
#12
b1100101011111110110010101111111011011110101011011011111011101111 9
#15
b110111011101111010101101101111101110111111001010111111101100101011111110 #
b110111011101111010101101101111101110111111001010111111101100101011111110 ,
b110111011100101011111110110010101111111011011110101011011011111011101111 5
18
#20
08
#22
b0001001000010010001101000011010001010110010101100111100001111000 9
#25
b110111011100101011111110110010101111111011011110101011011011111011101111 #
b110111011100101011111110110010101111111011011110101011011011111011101111 ,
b110111011101111010101101101111101110111111001010111111101100101011111110 /
b000100100001001000010010001101000011010001010110010101100111100001111000 5
18
#30
08
#32
b1101111010101101101111101110111111001010111111101100101011111110 9
#35
b000100100001001000010010001101000011010001010110010101100111100001111000 #
b000100100001001000010010001101000011010001010110010101100111100001111000 ,
b110111011100101011111110110010101111111011011110101011011011111011101111 /
b110111011101111010101101101111101110111111001010111111101100101011111110 5
18
#40
08
#42
b1100101011111110110010101111111011011110101011011011111011101111 9
#45
b110111011101111010101101101111101110111111001010111111101100101011111110 #
b110111011101111010101101101111101110111111001010111111101100101011111110 ,
b000100100001001000010010001101000011010001010110010101100111100001111000 /
b110111011100101011111110110010101111111011011110101011011011111011101111 5
18
#47
b110111011101111010101101101111101110111111001010111011101100101011111110 #
b00010101 &
b000000000000000000000000000000000000000000000000000100000000000000000000 '
1*
1+
b000000000000000000000000000000000000000000000000000100000000000000000000 ;
#50
08
#52
b0001001000010010001101000011010001010110010101100111100001111000 9
#55
b110111011100101011111110110010101111111011011110101111011011111011101111 #
b110111011100101011111110110010101111111011011110101011011011111011101111 ,
b110111011101111010101101101111101110111111001010111111101100101011111110 /
12
14
b000100100001001000010010001101000011010001010110010101100111100001111000 5
18
#60
08
#62
b1101111010101101101111101110111111001010111111101100101011111110 9
#65
b000100100001001000010010001101000011010001010110010001100111100001111000 #
b000100100001001000010010001101000011010001010110010101100111100001111000 ,
b110111011100101011111110110010101111111011011110101011011011111011101111 /
b110111011101111010101101101111101110111111001010111111101100101011111110 5
18
#70
08
#72
b1100101011111110110010101111111011011110101011011011111011101111 9
#75
b110111011101111010101101101111101110111111001010111011101100101011111110 #
b110111011101111010101101101111101110111111001010111111101100101011111110 ,
b000100100001001000010010001101000011010001010110010101100111100001111000 /
b110111011100101011111110110010101111111011011110101011011011111011101111 5
18
#77
b110111011101111110111101101111101110111111001010111111101100101011111110 #
b11000000 &
b000000000000000000000000000000000000000000000000000000000000000000000000 '
0+
b000000000000000100010000000000000000000000000000000000000000000000000000 ;
#80
08
#82
b0001001000010010001101000011010001010110010101100111100001111000 9
#85
b110111011100101111101110110010101111111011011110101011011011111011101111 #
b110111011100101011111110110010101111111011011110101011011011111011101111 ,
b110111011101111110111101101111101110111111001010111111101100101011111110 /
13
04
b000100100001001000010010001101000011010001010110010101100111100001111000 5
18
#90
08
#95
b000100100001001100000010001101000011010001010110010101100111100001111000 #
b000100100001001000010010001101000011010001010110010101100111100001111000 ,
b110111011100101111101110110010101111111011011110101011011011111011101111 /
18
#100
08
#105
b000100100001001100000010001101000011010001010110010101100111100001111000 /
18
